LICENSE.txt
MANIFEST.in
README.rst
setup.py
webthon/__init__.py
webthon.egg-info/PKG-INFO
webthon.egg-info/SOURCES.txt
webthon.egg-info/dependency_links.txt
webthon.egg-info/top_level.txt