Metadata-Version: 2.1
Name: webthon
Version: 0.0.1
Summary: This is simple html generator for flask or django
Home-page: UNKNOWN
Author: mario1842
Author-email: mario1842.info@gmail.com
License: MIT
Keywords: flask html css generator django
Platform: UNKNOWN
Classifier: Development Status :: 5 - Production/Stable
Classifier: Intended Audience :: Education
Classifier: Operating System :: Microsoft :: Windows :: Windows 10
Classifier: License :: OSI Approved :: MIT License
Classifier: Programming Language :: Python :: 3
License-File: LICENSE.txt
